{
  "id": "ef20acfc-1bc8-4596-bdba-c196ca2cdcb0",
  "prevId": "6896e51a-6c55-48a8-a481-9fb6d2d9f634",
  "version": "7",
  "dialect": "postgresql",
  "tables": {
    "public.example_table": {
      "name": "example_table",
      "schema": "",
      "columns": {
        "id": {
          "name": "id",
          "type": "uuid",
          "primaryKey": true,
          "notNull": true,
          "default": "gen_random_uuid()"
        },
        "user_id": {
          "name": "user_id",
          "type": "uuid",
          "primaryKey": false,
          "notNull": true
        },
        "todo_name": {
          "name": "todo_name",
          "type": "text",
          "primaryKey": false,
          "notNull": true
        },
        "created_at": {
          "name": "created_at",
          "type": "timestamp",
          "primaryKey": false,
          "notNull": false,
          "default": "now()"
        },
        "updated_at": {
          "name": "updated_at",
          "type": "timestamp",
          "primaryKey": false,
          "notNull": false,
          "default": "now()"
        }
      },
      "indexes": {},
      "foreignKeys": {
        "example_table_user_id_users_table_user_id_fk": {
          "name": "example_table_user_id_users_table_user_id_fk",
          "tableFrom": "example_table",
          "tableTo": "users_table",
          "columnsFrom": [
            "user_id"
          ],
          "columnsTo": [
            "user_id"
          ],
          "onDelete": "no action",
          "onUpdate": "no action"
        }
      },
      "compositePrimaryKeys": {},
      "uniqueConstraints": {}
    },
    "public.users_table": {
      "name": "users_table",
      "schema": "",
      "columns": {
        "id": {
          "name": "id",
          "type": "uuid",
          "primaryKey": true,
          "notNull": true,
          "default": "gen_random_uuid()"
        },
        "user_id": {
          "name": "user_id",
          "type": "uuid",
          "primaryKey": false,
          "notNull": true
        },
        "user_name": {
          "name": "user_name",
          "type": "varchar(255)",
          "primaryKey": false,
          "notNull": false
        },
        "created_at": {
          "name": "created_at",
          "type": "timestamp",
          "primaryKey": false,
          "notNull": false,
          "default": "now()"
        },
        "updated_at": {
          "name": "updated_at",
          "type": "timestamp",
          "primaryKey": false,
          "notNull": false,
          "default": "now()"
        }
      },
      "indexes": {},
      "foreignKeys": {},
      "compositePrimaryKeys": {},
      "uniqueConstraints": {
        "users_table_user_id_unique": {
          "name": "users_table_user_id_unique",
          "nullsNotDistinct": false,
          "columns": [
            "user_id"
          ]
        }
      }
    }
  },
  "enums": {},
  "schemas": {},
  "sequences": {},
  "_meta": {
    "columns": {},
    "schemas": {},
    "tables": {}
  }
}